gopublic/__init__.py
gopublic/cli/__init__.py
gopublic/cli/cli.py
gopublic/cli/config.py
gopublic/cli/decorators.py
gopublic/cli/io.py
gopublic/cli/commands/__init__.py
gopublic/cli/commands/cmd_file.py
gopublic/cli/commands/cmd_init.py
gopublic/cli/commands/cmd_token.py
gopublic/cli/commands/file/__init__.py
gopublic/cli/commands/file/delete.py
gopublic/cli/commands/file/list.py
gopublic/cli/commands/file/publish.py
gopublic/cli/commands/file/search.py
gopublic/cli/commands/file/tag.py
gopublic/cli/commands/file/unpublish.py
gopublic/cli/commands/file/untag.py
gopublic/cli/commands/file/view.py
gopublic/cli/commands/token/__init__.py
gopublic/cli/commands/token/create.py
gopublic/golib/__init__.py
gopublic/golib/client.py
gopublic/golib/exceptions.py
gopublic/golib/file/__init__.py
gopublic/golib/token/__init__.py
gopublic-0.0.7.dist-info/LICENSE
gopublic-0.0.7.dist-info/METADATA
gopublic-0.0.7.dist-info/WHEEL
gopublic-0.0.7.dist-info/entry_points.txt
gopublic-0.0.7.dist-info/top_level.txt
gopublic-0.0.7.dist-info/RECORD
